RnaChipIntegrator-3.0.0.data/data/RnaChipIntegrator/CHANGELOG.rst
RnaChipIntegrator-3.0.0.data/data/RnaChipIntegrator/LICENSE
RnaChipIntegrator-3.0.0.data/data/RnaChipIntegrator/README.rst
rnachipintegrator/Features.py
rnachipintegrator/Peaks.py
rnachipintegrator/__init__.py
rnachipintegrator/analysis.py
rnachipintegrator/cli.py
rnachipintegrator/distances.py
rnachipintegrator/output.py
rnachipintegrator/utils.py
rnachipintegrator/xls_output.py
RnaChipIntegrator-3.0.0.dist-info/LICENSE
RnaChipIntegrator-3.0.0.dist-info/METADATA
RnaChipIntegrator-3.0.0.dist-info/WHEEL
RnaChipIntegrator-3.0.0.dist-info/entry_points.txt
RnaChipIntegrator-3.0.0.dist-info/top_level.txt
RnaChipIntegrator-3.0.0.dist-info/RECORD
