Metadata-Version: 2.1
Name: RnaChipIntegrator
Version: 3.0.0
Summary: Analyse genes against peak data, and vice versa
Home-page: https://github.com/fls-bioinformatics-core/RnaChipIntegrator
Download-URL: https://github.com/fls-bioinformatics-core/RnaChipIntegrator/archive/v3.0.0.tar.gz
Author: Peter Briggs, Ian Donaldson, Leo Zeef
Author-email: peter.briggs@manchester.ac.uk
Maintainer: Peter Briggs
Maintainer-email: peter.briggs@manchester.ac.uk
License: Artistic License
Keywords: RnaChipIntegrator
Classifier: Development Status :: 5 - Production/Stable
Classifier: Intended Audience :: Science/Research
Classifier: Environment :: Console
Classifier: License :: OSI Approved :: Artistic License
Classifier: Operating System :: POSIX
Classifier: Topic :: Scientific/Engineering :: Bio-Informatics
Classifier: Natural Language :: English
Classifier: Programming Language :: Python :: 3
Classifier: Programming Language :: Python :: 3.6
Classifier: Programming Language :: Python :: 3.7
Classifier: Programming Language :: Python :: 3.8
Classifier: Programming Language :: Python :: 3.9
License-File: LICENSE
Requires-Dist: xlsxwriter >=0.8.4
